{
  "comment": "Comprehensive DDJ-FLX4 input map, sourced from the official AlphaTheta 'DDJ-FLX4 List of MIDI messages' (Ver 1.0). This is a superset of control-map.json: control-map.json remains the single source of truth for the 17 deck-rendered/lesson-usable controls (unchanged responsibility); this file adds every other documented physical input for Hardware Lab's comprehensive diagnostics and the physical verification sweep. See docs/creative-mix-studio/RESEARCH.md for the full derivation, byte-by-byte source notes, and documented scope decisions (SHIFT combinations, Vinyl On/Off, one ambiguous NOTE-67 row, performance-pad generation formula). behaviorStatus is one of: functional (drives real audio via audio-engine.js), pending (recognized, no musical behavior implemented yet), unsupported (this app's architecture cannot drive it: no mic input path, no separate headphone/cue audio output). Performance pad presses (8 pads x 7 modes x 2 decks = 112 addresses) are generated at runtime by index.html from the verified formula documented below and in RESEARCH.md, not hand-transcribed here. pos (left/top/width/height, percent of the deck image) is only present on 'deck1-*' and deck-neutral entries; a matching 'deck2-*' entry with no pos of its own is mirrored at load time by shifting left by deckMirrorOffsetPercent (see docs/creative-mix-studio/RESEARCH.md 'Complete Visual and Action Parity' for how this offset and every pos value were calibrated against the real deck image, and its accuracy caveats). Entries with no pos and no deck2 sibling to mirror from are diagnostics-only this cycle (no deck hotspot) -- see the same doc section for which ones and why.",
  "padFormula": {
    "description": "note = modeIndex*16 + (padIndex-1), padIndex 1..8, modeIndex 0..7 in order [hotcue,padfx1,beatjump,sampler,keyboard,padfx2,beatloop,keyshift]. Channel: deck1=dec8(status 0x97), deck2=dec10(status 0x99). Verified against Pad 1, Pad 2, and Pad 8's full rows in the source PDF.",
    "modes": ["hotcue", "padfx1", "beatjump", "sampler", "keyboard", "padfx2", "beatloop", "keyshift"],
    "deck1Status": 151,
    "deck2Status": 153
  },
  "deckMirrorOffsetPercent": 62.7,
  "padGrid": {
    "description": "Performance pad and pad-mode-button visual positions, calibrated against the deck image the same way as every other pos value here. Applies to both the 4 pad-mode buttons (row above the pads) and the 8 pads themselves (2 rows x 4 columns) generated by index.html's generatePadEntries().",
    "modeButtonColumnLeft": [9.92, 14.35, 18.78, 23.21],
    "modeButtonTop": 72.99,
    "modeButtonWidth": 3.67,
    "modeButtonHeight": 2.58,
    "padColumnLeft": [9.75, 14.18, 18.61, 23.0],
    "padRowTop": [78.83, 86.8],
    "padWidth": 4.05,
    "padHeight": 7.21
  },
  "groups": [
    {
      "id": "deck",
      "label": "Deck",
      "entries": [
        { "id": "deck1-shift", "label": "Deck 1 Shift", "deck": "1", "kind": "button", "match": { "type": 144, "channel": 0, "number": 63 }, "behaviorStatus": "pending", "note": "Modifier held while pressing other deck controls; SHIFT-combination addresses are not separately modeled this cycle.", "pos": { "left": "5.02%", "top": "67%", "width": "2.53%", "height": "3.72%" } },
        { "id": "deck2-shift", "label": "Deck 2 Shift", "deck": "2", "kind": "button", "match": { "type": 144, "channel": 1, "number": 63 }, "behaviorStatus": "pending", "note": "Same as Deck 1 Shift." },
        { "id": "deck1-jog-touch", "label": "Deck 1 Jog Touch", "deck": "1", "kind": "button", "match": { "type": 144, "channel": 0, "number": 54 }, "behaviorStatus": "pending", "note": "Platter touch/press. No scratch audio implemented.", "pos": { "left": "5.02%", "top": "19.8%", "width": "26.75%", "height": "48.18%" } },
        { "id": "deck2-jog-touch", "label": "Deck 2 Jog Touch", "deck": "2", "kind": "button", "match": { "type": 144, "channel": 1, "number": 54 }, "behaviorStatus": "pending" },
        { "id": "deck1-jog-rotate", "label": "Deck 1 Jog Rotate (platter)", "deck": "1", "kind": "relative", "match": { "type": 176, "channel": 0, "number": 34 }, "altNumbers": [35], "behaviorStatus": "pending", "note": "Relative encoder. Real address depends on hardware vinyl-mode state (CC 34 or 35); both are treated as jog rotation. No scratch/pitch-bend audio implemented.", "pos": { "left": "5.02%", "top": "19.8%", "width": "26.75%", "height": "48.18%" } },
        { "id": "deck2-jog-rotate", "label": "Deck 2 Jog Rotate (platter)", "deck": "2", "kind": "relative", "match": { "type": 176, "channel": 1, "number": 34 }, "altNumbers": [35], "behaviorStatus": "pending" },
        { "id": "deck1-jog-wheel-rotate", "label": "Deck 1 Jog Rotate (wheel edge)", "deck": "1", "kind": "relative", "match": { "type": 176, "channel": 0, "number": 33 }, "behaviorStatus": "pending", "pos": { "left": "5.02%", "top": "19.8%", "width": "26.75%", "height": "48.18%" } },
        { "id": "deck2-jog-wheel-rotate", "label": "Deck 2 Jog Rotate (wheel edge)", "deck": "2", "kind": "relative", "match": { "type": 176, "channel": 1, "number": 33 }, "behaviorStatus": "pending" },
        { "id": "deck1-loop-in", "label": "Deck 1 Loop IN", "deck": "1", "kind": "button", "match": { "type": 144, "channel": 0, "number": 16 }, "behaviorStatus": "pending", "pos": { "left": "4.94%", "top": "11.08%", "width": "2.7%", "height": "4.78%" } },
        { "id": "deck2-loop-in", "label": "Deck 2 Loop IN", "deck": "2", "kind": "button", "match": { "type": 144, "channel": 1, "number": 16 }, "behaviorStatus": "pending" },
        { "id": "deck1-loop-out", "label": "Deck 1 Loop OUT", "deck": "1", "kind": "button", "match": { "type": 144, "channel": 0, "number": 17 }, "behaviorStatus": "pending", "pos": { "left": "10.04%", "top": "11.08%", "width": "2.66%", "height": "4.78%" } },
        { "id": "deck2-loop-out", "label": "Deck 2 Loop OUT", "deck": "2", "kind": "button", "match": { "type": 144, "channel": 1, "number": 17 }, "behaviorStatus": "pending" },
        { "id": "deck1-loop-4beat-exit", "label": "Deck 1 4 Beat / Exit", "deck": "1", "kind": "button", "match": { "type": 144, "channel": 0, "number": 77 }, "behaviorStatus": "pending", "pos": { "left": "15.49%", "top": "11.84%", "width": "1.86%", "height": "3.26%" } },
        { "id": "deck2-loop-4beat-exit", "label": "Deck 2 4 Beat / Exit", "deck": "2", "kind": "button", "match": { "type": 144, "channel": 1, "number": 77 }, "behaviorStatus": "pending" },
        { "id": "deck1-loop-call-left", "label": "Deck 1 Cue/Loop Call ◁", "deck": "1", "kind": "button", "match": { "type": 144, "channel": 0, "number": 81 }, "behaviorStatus": "pending", "pos": { "left": "20.72%", "top": "12.06%", "width": "1.56%", "height": "2.81%" } },
        { "id": "deck2-loop-call-left", "label": "Deck 2 Cue/Loop Call ◁", "deck": "2", "kind": "button", "match": { "type": 144, "channel": 1, "number": 81 }, "behaviorStatus": "pending" },
        { "id": "deck1-loop-call-right", "label": "Deck 1 Cue/Loop Call ▷", "deck": "1", "kind": "button", "match": { "type": 144, "channel": 0, "number": 83 }, "behaviorStatus": "pending", "pos": { "left": "24.89%", "top": "12.06%", "width": "1.56%", "height": "2.81%" } },
        { "id": "deck2-loop-call-right", "label": "Deck 2 Cue/Loop Call ▷", "deck": "2", "kind": "button", "match": { "type": 144, "channel": 1, "number": 83 }, "behaviorStatus": "pending" },
        { "id": "deck1-beat-sync", "label": "Deck 1 Beat Sync", "deck": "1", "kind": "button", "match": { "type": 144, "channel": 0, "number": 88 }, "behaviorStatus": "pending", "note": "Per the official spec, this button sends its MIDI message on release, not on press.", "pos": { "left": "29.03%", "top": "10.85%", "width": "2.91%", "height": "5.31%" } },
        { "id": "deck2-beat-sync", "label": "Deck 2 Beat Sync", "deck": "2", "kind": "button", "match": { "type": 144, "channel": 1, "number": 88 }, "behaviorStatus": "pending" },
        { "id": "deck1-hotcue-mode", "label": "Deck 1 Hot Cue Mode", "deck": "1", "kind": "button", "match": { "type": 144, "channel": 0, "number": 27 }, "behaviorStatus": "pending" },
        { "id": "deck2-hotcue-mode", "label": "Deck 2 Hot Cue Mode", "deck": "2", "kind": "button", "match": { "type": 144, "channel": 1, "number": 27 }, "behaviorStatus": "pending" },
        { "id": "deck1-padfx1-mode", "label": "Deck 1 Pad FX 1 Mode", "deck": "1", "kind": "button", "match": { "type": 144, "channel": 0, "number": 30 }, "behaviorStatus": "pending" },
        { "id": "deck2-padfx1-mode", "label": "Deck 2 Pad FX 1 Mode", "deck": "2", "kind": "button", "match": { "type": 144, "channel": 1, "number": 30 }, "behaviorStatus": "pending" },
        { "id": "deck1-beatjump-mode", "label": "Deck 1 Beat Jump Mode", "deck": "1", "kind": "button", "match": { "type": 144, "channel": 0, "number": 32 }, "behaviorStatus": "pending" },
        { "id": "deck2-beatjump-mode", "label": "Deck 2 Beat Jump Mode", "deck": "2", "kind": "button", "match": { "type": 144, "channel": 1, "number": 32 }, "behaviorStatus": "pending" },
        { "id": "deck1-sampler-mode", "label": "Deck 1 Sampler Mode", "deck": "1", "kind": "button", "match": { "type": 144, "channel": 0, "number": 34 }, "behaviorStatus": "pending" },
        { "id": "deck2-sampler-mode", "label": "Deck 2 Sampler Mode", "deck": "2", "kind": "button", "match": { "type": 144, "channel": 1, "number": 34 }, "behaviorStatus": "pending" }
      ]
    },
    {
      "id": "mixer",
      "label": "Mixer (beyond EQ / fader / crossfader)",
      "entries": [
        { "id": "trim-1", "label": "Channel 1 Trim", "deck": "1", "kind": "knob", "match": { "type": 176, "channel": 0, "number": 4 }, "behaviorStatus": "pending", "note": "audio-engine.js has no gain stage ahead of the EQ chain.", "pos": { "left": "44.43%", "top": "14.95%", "width": "2.62%", "height": "5.01%" } },
        { "id": "trim-2", "label": "Channel 2 Trim", "deck": "2", "kind": "knob", "match": { "type": 176, "channel": 1, "number": 4 }, "behaviorStatus": "pending", "pos": { "left": "52.36%", "top": "14.95%", "width": "2.66%", "height": "5.01%" } },
        { "id": "cfx-1", "label": "Channel 1 CFX", "deck": "1", "kind": "knob", "match": { "type": 176, "channel": 6, "number": 23 }, "behaviorStatus": "functional", "audioAction": "colorFx", "note": "Color FX knob, wired to a per-deck filter: left closes a low-pass, right opens a high-pass, centre is transparent. Per the official DDJ-FLX4 MIDI list, both decks' CFX share MIDI channel 7 (dec) -- this app's channel 6 -- and are told apart by CC number (23 vs 24), unlike TRIM/EQ which share one CC number and differ by channel. Addresses are spec-mapped, NOT confirmed on real hardware.", "pos": { "left": "44.26%", "top": "49.69%", "width": "3.04%", "height": "5.46%" } },
        { "id": "cfx-2", "label": "Channel 2 CFX", "deck": "2", "kind": "knob", "match": { "type": 176, "channel": 6, "number": 24 }, "behaviorStatus": "functional", "audioAction": "colorFx", "pos": { "left": "52.19%", "top": "49.69%", "width": "3.04%", "height": "5.46%" } },
        { "id": "master-level", "label": "Master Level", "deck": null, "kind": "knob", "match": { "type": 176, "channel": 6, "number": 8 }, "behaviorStatus": "functional", "audioAction": "masterGain", "visualTargetId": "master-volume", "note": "Drives audioEngine.setMasterGain(); already supported by audio-engine.js.", "pos": { "left": "59.24%", "top": "14.04%", "width": "3.67%", "height": "6.22%" } },
        { "id": "master-cue", "label": "Master Cue", "deck": null, "kind": "button", "match": { "type": 144, "channel": 6, "number": 99 }, "behaviorStatus": "unsupported", "note": "Headphone/cue monitor routing needs a second audio output; not implemented (no setSinkId support assumed).", "pos": { "left": "59.49%", "top": "24.73%", "width": "3.12%", "height": "2.81%" } },
        { "id": "mic-level", "label": "Mic Level", "deck": null, "kind": "knob", "match": { "type": 176, "channel": 6, "number": 5 }, "behaviorStatus": "unsupported", "note": "This app has no microphone-audio signal path to attenuate.", "pos": { "left": "36.84%", "top": "32.09%", "width": "3.08%", "height": "5.84%" } },
        { "id": "headphone-mix", "label": "Headphone Mix", "deck": null, "kind": "knob", "match": { "type": 176, "channel": 6, "number": 12 }, "behaviorStatus": "unsupported", "note": "No separate headphone/cue audio output implemented.", "pos": { "left": "36.84%", "top": "59.48%", "width": "3.08%", "height": "6.83%" } },
        { "id": "headphone-level", "label": "Headphone Level", "deck": null, "kind": "knob", "match": { "type": 176, "channel": 6, "number": 13 }, "behaviorStatus": "unsupported", "pos": { "left": "37.13%", "top": "69.95%", "width": "2.49%", "height": "4.78%" } },
        { "id": "smart-cfx", "label": "Smart CFX", "deck": null, "kind": "button", "match": { "type": 144, "channel": 6, "number": 0 }, "behaviorStatus": "pending", "pos": { "left": "36.92%", "top": "49.77%", "width": "2.91%", "height": "5.31%" } },
        { "id": "smart-fader", "label": "Smart Fader", "deck": null, "kind": "button", "match": { "type": 144, "channel": 6, "number": 1 }, "behaviorStatus": "pending", "pos": { "left": "36.92%", "top": "80.2%", "width": "2.91%", "height": "5.24%" } },
        { "id": "android-mono-stereo", "label": "Android MONO/STEREO", "deck": null, "kind": "button", "match": { "type": 144, "channel": 6, "number": 109 }, "behaviorStatus": "pending", "note": "No confirmed visible top-panel counterpart was identified during calibration (likely a rear/settings-area switch, similar to Vinyl Mode); diagnostics-only this cycle." }
      ]
    },
    {
      "id": "effects",
      "label": "Beat FX",
      "entries": [
        { "id": "fx-ch-select", "label": "FX Channel Select", "deck": null, "kind": "button", "match": { "type": 144, "channel": 4, "number": 16 }, "behaviorStatus": "pending", "note": "3-position switch (CH1 / CH2 / CH1&CH2); simplified to detecting activity on this address rather than modeling all combinations.", "pos": { "left": "59.24%", "top": "42.19%", "width": "3.67%", "height": "2.88%" } },
        { "id": "fx-select", "label": "FX Select", "deck": null, "kind": "button", "match": { "type": 144, "channel": 4, "number": 99 }, "behaviorStatus": "pending", "pos": { "left": "59.49%", "top": "51.06%", "width": "3.12%", "height": "2.81%" } },
        { "id": "beat-left", "label": "Beat ◁", "deck": null, "kind": "button", "match": { "type": 144, "channel": 4, "number": 74 }, "behaviorStatus": "pending", "pos": { "left": "58.48%", "top": "60.02%", "width": "2.24%", "height": "2.81%" } },
        { "id": "beat-right", "label": "Beat ▷", "deck": null, "kind": "button", "match": { "type": 144, "channel": 4, "number": 75 }, "behaviorStatus": "pending", "pos": { "left": "61.35%", "top": "60.02%", "width": "2.24%", "height": "2.81%" } },
        { "id": "fx-level-depth", "label": "Level/Depth", "deck": null, "kind": "knob", "match": { "type": 176, "channel": 4, "number": 2 }, "behaviorStatus": "pending", "pos": { "left": "59.58%", "top": "69.73%", "width": "3.04%", "height": "5.46%" } },
        { "id": "fx-onoff-ch1", "label": "FX On/Off (CH1)", "deck": "1", "kind": "button", "match": { "type": 144, "channel": 4, "number": 71 }, "behaviorStatus": "pending", "note": "CH1&CH2 position sends the same address as CH1; the CH-select switch determines which channel is affected. Shares its deck hotspot with FX On/Off (CH2) below -- the real hardware has one physical button here, not two.", "pos": { "left": "59.37%", "top": "79.82%", "width": "3.38%", "height": "6.07%" } },
        { "id": "fx-onoff-ch2", "label": "FX On/Off (CH2)", "deck": "2", "kind": "button", "match": { "type": 144, "channel": 5, "number": 71 }, "behaviorStatus": "pending", "note": "See FX On/Off (CH1) -- same physical button." }
      ]
    },
    {
      "id": "browse",
      "label": "Browse & Load",
      "entries": [
        { "id": "browse-rotate", "label": "Browse Rotate", "deck": null, "kind": "relative", "match": { "type": 176, "channel": 6, "number": 64 }, "behaviorStatus": "pending", "pos": { "left": "47.97%", "top": "5.46%", "width": "3.5%", "height": "6.3%" } },
        { "id": "browse-press", "label": "Browse Press", "deck": null, "kind": "button", "match": { "type": 144, "channel": 6, "number": 65 }, "behaviorStatus": "pending", "pos": { "left": "47.97%", "top": "5.46%", "width": "3.5%", "height": "6.3%" } },
        { "id": "deck1-load", "label": "Deck 1 Load", "deck": "1", "kind": "button", "match": { "type": 144, "channel": 6, "number": 70 }, "behaviorStatus": "pending", "note": "This app loads tracks via the Load Deck A/B file picker, not the controller.", "pos": { "left": "41.73%", "top": "8.57%", "width": "3.04%", "height": "2.58%" } },
        { "id": "deck2-load", "label": "Deck 2 Load", "deck": "2", "kind": "button", "match": { "type": 144, "channel": 6, "number": 71 }, "behaviorStatus": "pending", "pos": { "left": "54.68%", "top": "8.57%", "width": "3.04%", "height": "2.58%" } }
      ]
    }
  ]
}
